Classfile /D:/study/myproject4test/target/classes/com/wall/myproject4test/java/zzw/jvm/Person.class
  Last modified 2020-12-13; size 1198 bytes
  MD5 checksum c56836238aff387d1e966573213379f1
  Compiled from "Person.java"
public class com.wall.myproject4test.java.zzw.jvm.Person
  minor version: 0
  major version: 52
  flags: ACC_PUBLIC, ACC_SUPER
Constant pool:
   #1 = Methodref          #10.#47        // java/lang/Object."<init>":()V
   #2 = String             #48            // Jack
   #3 = Fieldref           #13.#49        // com/wall/myproject4test/java/zzw/jvm/Person.name:Ljava/lang/String;
   #4 = Double             100.0d
   #6 = Fieldref           #13.#50        // com/wall/myproject4test/java/zzw/jvm/Person.salary:D
   #7 = Fieldref           #51.#52        // java/lang/System.out:Ljava/io/PrintStream;
   #8 = String             #53            // person say...
   #9 = Methodref          #54.#55        // java/io/PrintStream.println:(Ljava/lang/String;)V
  #10 = Class              #56            // java/lang/Object
  #11 = Methodref          #13.#57        // com/wall/myproject4test/java/zzw/jvm/Person.calc:(II)I
  #12 = Fieldref           #13.#58        // com/wall/myproject4test/java/zzw/jvm/Person.obj:Ljava/lang/Object;
  #13 = Class              #59            // com/wall/myproject4test/java/zzw/jvm/Person
  #14 = Utf8               name
  #15 = Utf8               Ljava/lang/String;
  #16 = Utf8               age
  #17 = Utf8               I
  #18 = Utf8               salary
  #19 = Utf8               D
  #20 = Utf8               ConstantValue
  #21 = Utf8               address
  #22 = Utf8               hobby
  #23 = String             #60            // Programming
  #24 = Utf8               obj
  #25 = Utf8               Ljava/lang/Object;
  #26 = Utf8               <init>
  #27 = Utf8               ()V
  #28 = Utf8               Code
  #29 = Utf8               LineNumberTable
  #30 = Utf8               LocalVariableTable
  #31 = Utf8               this
  #32 = Utf8               Lcom/wall/myproject4test/java/zzw/jvm/Person;
  #33 = Utf8               say
  #34 = Utf8               calc
  #35 = Utf8               (II)I
  #36 = Utf8               op1
  #37 = Utf8               op2
  #38 = Utf8               result
  #39 = Utf8               MethodParameters
  #40 = Utf8               main
  #41 = Utf8               ([Ljava/lang/String;)V
  #42 = Utf8               args
  #43 = Utf8               [Ljava/lang/String;
  #44 = Utf8               <clinit>
  #45 = Utf8               SourceFile
  #46 = Utf8               Person.java
  #47 = NameAndType        #26:#27        // "<init>":()V
  #48 = Utf8               Jack
  #49 = NameAndType        #14:#15        // name:Ljava/lang/String;
  #50 = NameAndType        #18:#19        // salary:D
  #51 = Class              #61            // java/lang/System
  #52 = NameAndType        #62:#63        // out:Ljava/io/PrintStream;
  #53 = Utf8               person say...
  #54 = Class              #64            // java/io/PrintStream
  #55 = NameAndType        #65:#66        // println:(Ljava/lang/String;)V
  #56 = Utf8               java/lang/Object
  #57 = NameAndType        #34:#35        // calc:(II)I
  #58 = NameAndType        #24:#25        // obj:Ljava/lang/Object;
  #59 = Utf8               com/wall/myproject4test/java/zzw/jvm/Person
  #60 = Utf8               Programming
  #61 = Utf8               java/lang/System
  #62 = Utf8               out
  #63 = Utf8               Ljava/io/PrintStream;
  #64 = Utf8               java/io/PrintStream
  #65 = Utf8               println
  #66 = Utf8               (Ljava/lang/String;)V
{
  private java.lang.String name;
    descriptor: Ljava/lang/String;
    flags: ACC_PRIVATE

  private int age;
    descriptor: I
    flags: ACC_PRIVATE

  private final double salary;
    descriptor: D
    flags: ACC_PRIVATE, ACC_FINAL
    ConstantValue: double 100.0d

  private static java.lang.String address;
    descriptor: Ljava/lang/String;
    flags: ACC_PRIVATE, ACC_STATIC

  private static final java.lang.String hobby;
    descriptor: Ljava/lang/String;
    flags: ACC_PRIVATE, ACC_STATIC, ACC_FINAL
    ConstantValue: String Programming

  private static java.lang.Object obj;
    descriptor: Ljava/lang/Object;
    flags: ACC_PRIVATE, ACC_STATIC

  public com.wall.myproject4test.java.zzw.jvm.Person();
    descriptor: ()V
    flags: ACC_PUBLIC
    Code:
      stack=3, locals=1, args_size=1
         0: aload_0
         1: invokespecial #1                  // Method java/lang/Object."<init>":()V
         4: aload_0
         5: ldc           #2                  // String Jack
         7: putfield      #3                  // Field name:Ljava/lang/String;
        10: aload_0
        11: ldc2_w        #4                  // double 100.0d
        14: putfield      #6                  // Field salary:D
        17: return
      LineNumberTable:
        line 3: 0
        line 4: 4
        line 6: 10
      LocalVariableTable:
        Start  Length  Slot  Name   Signature
            0      18     0  this   Lcom/wall/myproject4test/java/zzw/jvm/Person;

  public void say();
    descriptor: ()V
    flags: ACC_PUBLIC
    Code:
      stack=2, locals=1, args_size=1
         0: getstatic     #7                  // Field java/lang/System.out:Ljava/io/PrintStream;
         3: ldc           #8                  // String person say...
         5: invokevirtual #9                  // Method java/io/PrintStream.println:(Ljava/lang/String;)V
         8: return
      LineNumberTable:
        line 11: 0
        line 12: 8
      LocalVariableTable:
        Start  Length  Slot  Name   Signature
            0       9     0  this   Lcom/wall/myproject4test/java/zzw/jvm/Person;

  public static int calc(int, int);
    descriptor: (II)I
    flags: ACC_PUBLIC, ACC_STATIC
    Code:
      stack=2, locals=4, args_size=2
         0: iconst_3
         1: istore_0
         2: iload_0
         3: iload_1
         4: iadd
         5: istore_2
         6: new           #10                 // class java/lang/Object
         9: dup
        10: invokespecial #1                  // Method java/lang/Object."<init>":()V
        13: astore_3
        14: iload_2
        15: ireturn
      LineNumberTable:
        line 14: 0
        line 15: 2
        line 16: 6
        line 17: 14
      LocalVariableTable:
        Start  Length  Slot  Name   Signature
            0      16     0   op1   I
            0      16     1   op2   I
            6      10     2 result   I
           14       2     3   obj   Ljava/lang/Object;
    MethodParameters:
      Name                           Flags
      op1
      op2

  public static void main(java.lang.String[]);
    descriptor: ([Ljava/lang/String;)V
    flags: ACC_PUBLIC, ACC_STATIC
    Code:
      stack=2, locals=1, args_size=1
         0: iconst_1
         1: iconst_2
         2: invokestatic  #11                 // Method calc:(II)I
         5: pop
         6: return
      LineNumberTable:
        line 20: 0
        line 21: 6
      LocalVariableTable:
        Start  Length  Slot  Name   Signature
            0       7     0  args   [Ljava/lang/String;
    MethodParameters:
      Name                           Flags
      args

  static {};
    descriptor: ()V
    flags: ACC_STATIC
    Code:
      stack=2, locals=0, args_size=0
         0: new           #10                 // class java/lang/Object
         3: dup
         4: invokespecial #1                  // Method java/lang/Object."<init>":()V
         7: putstatic     #12                 // Field obj:Ljava/lang/Object;
        10: return
      LineNumberTable:
        line 9: 0
}
SourceFile: "Person.java"
